bsescraper/__init__.py
bsescraper-1.0.6.dist-info/LICENSE
bsescraper-1.0.6.dist-info/METADATA
bsescraper-1.0.6.dist-info/WHEEL
bsescraper-1.0.6.dist-info/top_level.txt
bsescraper-1.0.6.dist-info/RECORD
