Metadata-Version: 2.1
Name: bsescraper
Version: 1.0.6
Summary: A python module to scrape the BSE INDIA website for all stock related data.
Author-email: Vedant Joshi <vedant.joshi10may@gmail.com>
Classifier: Programming Language :: Python :: 3
Classifier: License :: OSI Approved :: MIT License
Classifier: Operating System :: OS Independent
Classifier: Topic :: Office/Business :: Financial
Classifier: Topic :: Software Development :: Libraries :: Python Modules
Requires-Python: >=3.7
License-File: LICENSE
